{
    "status": "SATISFIED",
    "solution": {
        "start_time": [
            [
                225,
                263,
                182,
                63,
                0,
                132,
                164,
                52,
                98,
                299
            ],
            [
                0,
                126,
                147,
                335,
                37,
                60,
                83,
                302,
                343,
                176
            ],
            [
                154,
                335,
                232,
                305,
                70,
                111,
                0,
                266,
                194,
                132
            ],
            [
                37,
                147,
                76,
                343,
                22,
                0,
                381,
                285,
                302,
                92
            ],
            [
                194,
                0,
                337,
                244,
                112,
                225,
                130,
                20,
                169,
                367
            ],
            [
                111,
                299,
                206,
                129,
                143,
                83,
                40,
                227,
                137,
                0
            ]
        ],
        "end_time": [
            [
                263,
                299,
                206,
                98,
                21,
                159,
                182,
                63,
                114,
                326
            ],
            [
                37,
                147,
                176,
                343,
                60,
                83,
                126,
                326,
                361,
                205
            ],
            [
                194,
                380,
                266,
                335,
                111,
                132,
                26,
                273,
                232,
                154
            ],
            [
                76,
                192,
                92,
                381,
                33,
                22,
                410,
                302,
                343,
                131
            ],
            [
                225,
                20,
                367,
                266,
                130,
                244,
                164,
                52,
                194,
                410
            ],
            [
                129,
                335,
                227,
                137,
                177,
                111,
                82,
                266,
                143,
                40
            ]
        ],
        "SpeedScaling": [
            [
                5,
                5,
                5,
                5,
                5,
                5,
                5,
                5,
                5,
                5
            ],
            [
                5,
                5,
                5,
                5,
                5,
                5,
                5,
                5,
                5,
                5
            ],
            [
                5,
                5,
                5,
                5,
                5,
                5,
                5,
                5,
                5,
                5
            ],
            [
                5,
                5,
                5,
                5,
                5,
                5,
                5,
                5,
                5,
                5
            ],
            [
                5,
                5,
                5,
                5,
                5,
                5,
                5,
                5,
                5,
                5
            ],
            [
                5,
                5,
                5,
                5,
                5,
                5,
                5,
                5,
                5,
                5
            ]
        ],
        "_output_item": "makespan=410\nenergy=4554\nidle=2445\nstart_times = [225, 263, 182, 63, 0, 132, 164, 52, 98, 299, 0, 126, 147, 335, 37, 60, 83, 302, 343, 176, 154, 335, 232, 305, 70, 111, 0, 266, 194, 132, 37, 147, 76, 343, 22, 0, 381, 285, 302, 92, 194, 0, 337, 244, 112, 225, 130, 20, 169, 367, 111, 299, 206, 129, 143, 83, 40, 227, 137, 0]\nend_times =[263, 299, 206, 98, 21, 159, 182, 63, 114, 326, 37, 147, 176, 343, 60, 83, 126, 326, 361, 205, 194, 380, 266, 335, 111, 132, 26, 273, 232, 154, 76, 192, 92, 381, 33, 22, 410, 302, 343, 131, 225, 20, 367, 266, 130, 244, 164, 52, 194, 410, 129, 335, 227, 137, 177, 111, 82, 266, 143, 40]\nspeed_assignment =[5, 5, 5, 5, 5, 5, 5, 5, 5, 5, 5, 5, 5, 5, 5, 5, 5, 5, 5, 5, 5, 5, 5, 5, 5, 5, 5, 5, 5, 5, 5, 5, 5, 5, 5, 5, 5, 5, 5, 5, 5, 5, 5, 5, 5, 5, 5, 5, 5, 5, 5, 5, 5, 5, 5, 5, 5, 5, 5, 5]\ntimepro =[215, 74, 52, 43, 38, 205, 70, 50, 41, 36, 136, 47, 33, 27, 24, 198, 68, 48, 40, 35, 120, 41, 29, 24, 21, 155, 53, 38, 31, 27, 100, 34, 24, 20, 18, 65, 22, 16, 13, 11, 94, 32, 23, 19, 16, 153, 52, 37, 31, 27, 210, 72, 51, 42, 37, 119, 41, 29, 24, 21, 165, 57, 40, 33, 29, 48, 16, 11, 9, 8, 128, 44, 31, 26, 23, 132, 45, 32, 26, 23, 240, 83, 58, 48, 43, 134, 46, 33, 27, 24, 105, 36, 25, 21, 18, 165, 57, 40, 33, 29, 227, 78, 55, 46, 40, 253, 87, 62, 51, 45, 193, 66, 47, 39, 34, 168, 58, 41, 34, 30, 233, 80, 57, 47, 41, 120, 41, 29, 24, 21, 149, 51, 36, 30, 26, 41, 14, 10, 8, 7, 212, 73, 52, 43, 38, 125, 43, 30, 25, 22, 219, 75, 53, 44, 39, 251, 86, 61, 51, 45, 93, 32, 22, 18, 16, 215, 74, 52, 43, 38, 62, 21, 15, 12, 11, 123, 42, 30, 25, 22, 163, 56, 40, 33, 29, 97, 33, 23, 19, 17, 231, 79, 56, 47, 41, 220, 76, 54, 44, 39, 175, 60, 42, 35, 31, 112, 38, 27, 22, 20, 169, 58, 41, 34, 30, 124, 43, 30, 25, 22, 104, 36, 25, 21, 18, 106, 36, 26, 21, 19, 192, 66, 47, 39, 34, 180, 62, 44, 36, 32, 143, 49, 35, 29, 25, 239, 82, 58, 48, 43, 102, 35, 25, 20, 18, 204, 70, 50, 41, 36, 117, 40, 28, 23, 21, 44, 15, 10, 9, 8, 194, 67, 47, 39, 34, 157, 54, 38, 31, 28, 236, 81, 58, 48, 42, 217, 75, 53, 44, 39, 36, 12, 9, 7, 6, 222, 76, 54, 45, 40]\n",
        "_checker": ""
    },
    "statistics": {
        "paths": 0,
        "flatIntVars": 962,
        "flatIntConstraints": 1142,
        "evaluatedHalfReifiedConstraints": 300,
        "method": "satisfy",
        "flatTime": 128.76000000000002,
        "nodes": 1,
        "solveTime": 180.0,
        "time": 176.0,
        "nSolutions": 1,
        "lower_gap_ini": {
            "lower": -2376,
            "upper": 20258
        },
        "gap_end": {
            "lower": -2376,
            "upper": 20258
        }
    }
}