{
    "status": "ALL_SOLUTIONS",
    "solution": {
        "start_time": [
            [
                407,
                173,
                315,
                329,
                2164,
                76,
                46,
                109
            ],
            [
                428,
                0,
                293,
                173,
                193,
                341,
                315,
                255
            ],
            [
                2220,
                2130,
                2087,
                0,
                255,
                146,
                1997,
                213
            ],
            [
                328,
                226,
                363,
                311,
                146,
                117,
                76,
                0
            ],
            [
                122,
                92,
                68,
                192,
                2192,
                280,
                0,
                46
            ],
            [
                198,
                102,
                387,
                279,
                312,
                2187,
                2201,
                171
            ]
        ],
        "end_time": [
            [
                418,
                226,
                328,
                385,
                2192,
                109,
                76,
                171
            ],
            [
                452,
                92,
                315,
                192,
                224,
                428,
                341,
                293
            ],
            [
                2291,
                2220,
                2130,
                92,
                292,
                213,
                2087,
                255
            ],
            [
                363,
                286,
                386,
                328,
                191,
                146,
                117,
                45
            ],
            [
                192,
                102,
                87,
                279,
                2291,
                307,
                46,
                68
            ],
            [
                279,
                170,
                472,
                311,
                374,
                2201,
                2291,
                198
            ]
        ],
        "SpeedScaling": [
            [
                1,
                1,
                1,
                1,
                1,
                1,
                1,
                1
            ],
            [
                1,
                1,
                1,
                1,
                1,
                1,
                1,
                1
            ],
            [
                1,
                1,
                1,
                1,
                1,
                1,
                1,
                1
            ],
            [
                1,
                1,
                1,
                1,
                1,
                1,
                1,
                1
            ],
            [
                1,
                1,
                1,
                1,
                1,
                1,
                1,
                1
            ],
            [
                1,
                1,
                1,
                1,
                1,
                1,
                1,
                1
            ]
        ],
        "_output_item": "makespan=2291\nenergy=3054\nidle=16037\nstart_times = [407, 173, 315, 329, 2164, 76, 46, 109, 428, 0, 293, 173, 193, 341, 315, 255, 2220, 2130, 2087, 0, 255, 146, 1997, 213, 328, 226, 363, 311, 146, 117, 76, 0, 122, 92, 68, 192, 2192, 280, 0, 46, 198, 102, 387, 279, 312, 2187, 2201, 171]\nend_times =[418, 226, 328, 385, 2192, 109, 76, 171, 452, 92, 315, 192, 224, 428, 341, 293, 2291, 2220, 2130, 92, 292, 213, 2087, 255, 363, 286, 386, 328, 191, 146, 117, 45, 192, 102, 87, 279, 2291, 307, 46, 68, 279, 170, 472, 311, 374, 2201, 2291, 198]\nspeed_assignment =[1, 1, 1, 1, 1, 1, 1, 1, 1, 1, 1, 1, 1, 1, 1, 1, 1, 1, 1, 1, 1, 1, 1, 1, 1, 1, 1, 1, 1, 1, 1, 1, 1, 1, 1, 1, 1, 1, 1, 1, 1, 1, 1, 1, 1, 1, 1, 1]\ntimepro =[11, 53, 13, 56, 28, 33, 30, 62, 24, 92, 22, 19, 31, 87, 26, 38, 71, 90, 43, 92, 37, 67, 90, 42, 35, 60, 23, 17, 45, 29, 41, 45, 70, 10, 19, 87, 99, 27, 46, 22, 81, 68, 85, 32, 62, 14, 90, 27]\n",
        "_checker": ""
    },
    "statistics": {
        "paths": 0,
        "flatBoolVars": 240,
        "flatIntVars": 98,
        "flatBoolConstraints": 120,
        "flatIntConstraints": 464,
        "evaluatedHalfReifiedConstraints": 240,
        "method": "satisfy",
        "flatTime": 71.384,
        "time": 127.0,
        "nSolutions": 1,
        "objective": 0,
        "objectiveBound": 0,
        "boolVariables": 120,
        "failures": 0,
        "propagations": 1576,
        "solveTime": 22.368,
        "lower_gap_ini": {
            "lower": 22700,
            "upper": 24666
        },
        "gap_end": {
            "lower": 22700,
            "upper": 24666
        }
    }
}