{
    "status": "ALL_SOLUTIONS",
    "solution": {
        "start_time": [
            [
                134,
                6075,
                6032,
                6038
            ],
            [
                6090,
                0,
                53,
                131
            ],
            [
                122,
                134,
                86,
                58
            ],
            [
                179,
                67,
                26,
                0
            ],
            [
                38,
                12,
                0,
                86
            ],
            [
                91,
                145,
                8,
                26
            ],
            [
                66,
                38,
                97,
                103
            ]
        ],
        "end_time": [
            [
                178,
                6103,
                6038,
                6075
            ],
            [
                6103,
                12,
                86,
                165
            ],
            [
                134,
                144,
                97,
                77
            ],
            [
                221,
                92,
                53,
                19
            ],
            [
                62,
                38,
                8,
                103
            ],
            [
                122,
                170,
                26,
                58
            ],
            [
                91,
                66,
                103,
                131
            ]
        ],
        "SpeedScaling": [
            [
                4,
                4,
                4,
                4
            ],
            [
                4,
                4,
                4,
                4
            ],
            [
                4,
                4,
                4,
                4
            ],
            [
                4,
                4,
                4,
                4
            ],
            [
                4,
                4,
                4,
                4
            ],
            [
                4,
                4,
                4,
                4
            ],
            [
                4,
                4,
                4,
                4
            ]
        ],
        "_output_item": "makespan=6103\nenergy=2225\nidle=23772\nstart_times = [134, 6075, 6032, 6038, 6090, 0, 53, 131, 122, 134, 86, 58, 179, 67, 26, 0, 38, 12, 0, 86, 91, 145, 8, 26, 66, 38, 97, 103]\nend_times =[178, 6103, 6038, 6075, 6103, 12, 86, 165, 134, 144, 97, 77, 221, 92, 53, 19, 62, 38, 8, 103, 122, 170, 26, 58, 91, 66, 103, 131]\nspeed_assignment =[4, 4, 4, 4, 4, 4, 4, 4, 4, 4, 4, 4, 4, 4, 4, 4, 4, 4, 4, 4, 4, 4, 4, 4, 4, 4, 4, 4]\ntimepro =[246, 73, 52, 44, 159, 47, 34, 28, 34, 10, 7, 6, 206, 61, 44, 37, 76, 22, 16, 13, 71, 21, 15, 12, 184, 55, 39, 33, 193, 57, 41, 34, 71, 21, 15, 12, 59, 17, 12, 10, 61, 18, 13, 11, 108, 32, 23, 19, 238, 71, 51, 42, 143, 42, 30, 25, 151, 45, 32, 27, 110, 32, 23, 19, 138, 41, 29, 24, 146, 43, 31, 26, 45, 13, 9, 8, 99, 29, 21, 17, 175, 52, 37, 31, 140, 42, 30, 25, 103, 30, 22, 18, 182, 54, 39, 32, 139, 41, 29, 25, 156, 46, 33, 28, 34, 10, 7, 6, 157, 47, 33, 28]\n",
        "_checker": ""
    },
    "statistics": {
        "paths": 0,
        "flatBoolVars": 168,
        "flatIntVars": 167,
        "flatBoolConstraints": 84,
        "flatIntConstraints": 321,
        "evaluatedHalfReifiedConstraints": 168,
        "method": "satisfy",
        "flatTime": 63.449000000000005,
        "time": 124.0,
        "nSolutions": 1,
        "objective": 0,
        "objectiveBound": 0,
        "boolVariables": 234,
        "failures": 0,
        "propagations": 65,
        "solveTime": 29.284000000000002,
        "lower_gap_ini": {
            "lower": 3234,
            "upper": 3914
        },
        "gap_end": {
            "lower": 3234,
            "upper": 3914
        }
    }
}