{
    "status": "ALL_SOLUTIONS",
    "solution": {
        "start_time": [
            [
                1315,
                78,
                51,
                3189,
                1334
            ],
            [
                118,
                3225,
                342,
                956,
                559
            ],
            [
                925,
                0,
                1631,
                1712,
                74
            ],
            [
                24,
                1623,
                3189,
                161,
                50
            ],
            [
                309,
                294,
                71,
                34,
                0
            ],
            [
                78,
                45,
                34,
                0,
                151
            ],
            [
                544,
                500,
                0,
                57,
                107
            ]
        ],
        "end_time": [
            [
                1334,
                104,
                63,
                3209,
                1373
            ],
            [
                161,
                3241,
                384,
                998,
                595
            ],
            [
                950,
                28,
                1638,
                1735,
                106
            ],
            [
                44,
                1666,
                3222,
                182,
                74
            ],
            [
                353,
                307,
                87,
                50,
                34
            ],
            [
                118,
                78,
                45,
                34,
                184
            ],
            [
                551,
                527,
                13,
                94,
                151
            ]
        ],
        "SpeedScaling": [
            [
                2,
                2,
                2,
                2,
                2
            ],
            [
                2,
                2,
                2,
                2,
                2
            ],
            [
                2,
                2,
                2,
                2,
                2
            ],
            [
                2,
                2,
                2,
                2,
                2
            ],
            [
                2,
                2,
                2,
                2,
                2
            ],
            [
                2,
                2,
                2,
                2,
                2
            ],
            [
                2,
                2,
                2,
                2,
                2
            ]
        ],
        "_output_item": "makespan=3241\nenergy=2666\nidle=15252\nstart_times = [1315, 78, 51, 3189, 1334, 118, 3225, 342, 956, 559, 925, 0, 1631, 1712, 74, 24, 1623, 3189, 161, 50, 309, 294, 71, 34, 0, 78, 45, 34, 0, 151, 544, 500, 0, 57, 107]\nend_times =[1334, 104, 63, 3209, 1373, 161, 3241, 384, 998, 595, 950, 28, 1638, 1735, 106, 44, 1666, 3222, 182, 74, 353, 307, 87, 50, 34, 118, 78, 45, 34, 184, 551, 527, 13, 94, 151]\nspeed_assignment =[2, 2, 2, 2, 2, 2, 2, 2, 2, 2, 2, 2, 2, 2, 2, 2, 2, 2, 2, 2, 2, 2, 2, 2, 2, 2, 2, 2, 2, 2, 2, 2, 2, 2, 2]\ntimepro =[106, 19, 146, 26, 70, 12, 113, 20, 217, 39, 238, 43, 89, 16, 236, 42, 233, 42, 200, 36, 140, 25, 158, 28, 41, 7, 128, 23, 182, 32, 115, 20, 240, 43, 185, 33, 118, 21, 134, 24, 245, 44, 76, 13, 89, 16, 91, 16, 193, 34, 223, 40, 184, 33, 62, 11, 190, 34, 183, 33, 41, 7, 155, 27, 72, 13, 210, 37, 247, 44]\n",
        "_checker": ""
    },
    "statistics": {
        "paths": 0,
        "flatBoolVars": 210,
        "flatIntVars": 216,
        "flatBoolConstraints": 105,
        "flatIntConstraints": 430,
        "evaluatedHalfReifiedConstraints": 210,
        "method": "satisfy",
        "flatTime": 66.256,
        "time": 117.0,
        "nSolutions": 1,
        "objective": 0,
        "objectiveBound": 0,
        "boolVariables": 105,
        "failures": 0,
        "propagations": 0,
        "solveTime": 18.133,
        "lower_gap_ini": {
            "lower": 4099,
            "upper": 5503
        },
        "gap_end": {
            "lower": 4099,
            "upper": 5503
        }
    }
}