{
    "status": "SATISFIED",
    "solution": {
        "start_time": [
            [
                42,
                108,
                80,
                8162,
                94
            ],
            [
                80,
                56,
                8161,
                68,
                0
            ],
            [
                0,
                151,
                50,
                27,
                8199
            ],
            [
                8345,
                129,
                0,
                8198,
                8140
            ],
            [
                8361,
                8171,
                8198,
                8179,
                39
            ],
            [
                8175,
                8304,
                94,
                8261,
                8239
            ],
            [
                8140,
                0,
                8218,
                8304,
                8313
            ]
        ],
        "end_time": [
            [
                80,
                129,
                94,
                8170,
                108
            ],
            [
                111,
                68,
                8198,
                80,
                39
            ],
            [
                27,
                182,
                80,
                50,
                8239
            ],
            [
                8361,
                151,
                31,
                8229,
                8170
            ],
            [
                8404,
                8179,
                8218,
                8198,
                73
            ],
            [
                8201,
                8344,
                125,
                8304,
                8261
            ],
            [
                8175,
                30,
                8256,
                8313,
                8404
            ]
        ],
        "SpeedScaling": [
            [
                4,
                4,
                4,
                2,
                4
            ],
            [
                4,
                4,
                4,
                4,
                4
            ],
            [
                4,
                4,
                4,
                4,
                4
            ],
            [
                4,
                4,
                4,
                4,
                4
            ],
            [
                1,
                4,
                4,
                4,
                4
            ],
            [
                4,
                4,
                4,
                4,
                4
            ],
            [
                4,
                4,
                4,
                4,
                1
            ]
        ],
        "_output_item": "makespan=8404\nenergy=2648\nidle=41024\nstart_times = [42, 108, 80, 8162, 94, 80, 56, 8161, 68, 0, 0, 151, 50, 27, 8199, 8345, 129, 0, 8198, 8140, 8361, 8171, 8198, 8179, 39, 8175, 8304, 94, 8261, 8239, 8140, 0, 8218, 8304, 8313]\nend_times =[80, 129, 94, 8170, 108, 111, 68, 8198, 80, 39, 27, 182, 80, 50, 8239, 8361, 151, 31, 8229, 8170, 8404, 8179, 8218, 8198, 73, 8201, 8344, 125, 8304, 8261, 8175, 30, 8256, 8313, 8404]\nspeed_assignment =[4, 4, 4, 2, 4, 4, 4, 4, 4, 4, 4, 4, 4, 4, 4, 4, 4, 4, 4, 4, 1, 4, 4, 4, 4, 4, 4, 4, 4, 4, 4, 4, 4, 4, 1]\ntimepro =[216, 64, 46, 38, 121, 36, 25, 21, 79, 23, 16, 14, 29, 8, 6, 5, 83, 24, 17, 14, 172, 51, 37, 31, 72, 21, 15, 12, 210, 62, 45, 37, 66, 19, 14, 12, 218, 65, 46, 39, 151, 45, 32, 27, 172, 51, 37, 31, 172, 51, 36, 30, 132, 39, 28, 23, 226, 67, 48, 40, 94, 28, 20, 16, 123, 36, 26, 22, 172, 51, 37, 31, 175, 52, 37, 31, 170, 50, 36, 30, 43, 13, 9, 7, 48, 14, 10, 8, 115, 34, 24, 20, 106, 31, 22, 19, 191, 57, 41, 34, 145, 43, 31, 26, 224, 66, 48, 40, 177, 53, 38, 31, 242, 72, 52, 43, 123, 36, 26, 22, 196, 58, 42, 35, 171, 51, 36, 30, 213, 63, 45, 38, 51, 15, 10, 9, 91, 27, 19, 16]\n",
        "_checker": ""
    },
    "statistics": {
        "paths": 0,
        "flatIntVars": 562,
        "flatIntConstraints": 632,
        "evaluatedHalfReifiedConstraints": 210,
        "method": "satisfy",
        "flatTime": 103.799,
        "nodes": 0,
        "solveTime": 65.0,
        "time": 186.0,
        "nSolutions": 1,
        "lower_gap_ini": {
            "lower": 4771,
            "upper": 5509
        },
        "gap_end": {
            "lower": 4771,
            "upper": 5509
        }
    }
}