{
    "status": "SATISFIED",
    "solution": {
        "start_time": [
            [
                142,
                213,
                163,
                149,
                258,
                182,
                76
            ],
            [
                273,
                163,
                123,
                342,
                304,
                251,
                38
            ],
            [
                336,
                0,
                80,
                245,
                123,
                270,
                311
            ],
            [
                251,
                273,
                38,
                0,
                48,
                205,
                24
            ],
            [
                160,
                113,
                188,
                364,
                180,
                154,
                132
            ],
            [
                13,
                258,
                273,
                235,
                342,
                0,
                198
            ],
            [
                149,
                285,
                0,
                135,
                228,
                160,
                96
            ]
        ],
        "end_time": [
            [
                149,
                258,
                182,
                163,
                303,
                205,
                96
            ],
            [
                304,
                200,
                163,
                364,
                342,
                270,
                76
            ],
            [
                378,
                40,
                123,
                270,
                155,
                311,
                336
            ],
            [
                273,
                285,
                48,
                24,
                71,
                251,
                38
            ],
            [
                180,
                132,
                208,
                584,
                188,
                160,
                154
            ],
            [
                31,
                273,
                281,
                245,
                387,
                13,
                235
            ],
            [
                160,
                437,
                14,
                149,
                258,
                171,
                132
            ]
        ],
        "SpeedScaling": [
            [
                2,
                2,
                2,
                2,
                2,
                2,
                2
            ],
            [
                2,
                2,
                2,
                2,
                2,
                2,
                2
            ],
            [
                2,
                2,
                2,
                2,
                2,
                2,
                2
            ],
            [
                2,
                2,
                2,
                2,
                2,
                2,
                2
            ],
            [
                2,
                2,
                2,
                1,
                2,
                2,
                2
            ],
            [
                2,
                2,
                2,
                2,
                2,
                2,
                2
            ],
            [
                2,
                1,
                2,
                2,
                2,
                2,
                2
            ]
        ],
        "_output_item": "makespan=584\nenergy=3712\nidle=2562\nstart_times = [142, 213, 163, 149, 258, 182, 76, 273, 163, 123, 342, 304, 251, 38, 336, 0, 80, 245, 123, 270, 311, 251, 273, 38, 0, 48, 205, 24, 160, 113, 188, 364, 180, 154, 132, 13, 258, 273, 235, 342, 0, 198, 149, 285, 0, 135, 228, 160, 96]\nend_times =[149, 258, 182, 163, 303, 205, 96, 304, 200, 163, 364, 342, 270, 76, 378, 40, 123, 270, 155, 311, 336, 273, 285, 48, 24, 71, 251, 38, 180, 132, 208, 584, 188, 160, 154, 31, 273, 281, 245, 387, 13, 235, 160, 437, 14, 149, 258, 171, 132]\nspeed_assignment =[2, 2, 2, 2, 2, 2, 2, 2, 2, 2, 2, 2, 2, 2, 2, 2, 2, 2, 2, 2, 2, 2, 2, 2, 2, 2, 2, 2, 2, 2, 2, 1, 2, 2, 2, 2, 2, 2, 2, 2, 2, 2, 2, 1, 2, 2, 2, 2, 2]\ntimepro =[41, 7, 252, 45, 109, 19, 83, 14, 254, 45, 128, 23, 115, 20, 172, 31, 207, 37, 224, 40, 126, 22, 214, 38, 107, 19, 214, 38, 237, 42, 225, 40, 242, 43, 139, 25, 181, 32, 232, 41, 144, 25, 123, 22, 69, 12, 57, 10, 136, 24, 130, 23, 257, 46, 80, 14, 112, 20, 109, 19, 116, 20, 220, 39, 47, 8, 33, 6, 125, 22, 101, 18, 88, 15, 44, 8, 60, 10, 252, 45, 77, 13, 210, 37, 61, 11, 152, 27, 83, 14, 82, 14, 166, 30, 65, 11, 203, 36]\n",
        "_checker": ""
    },
    "statistics": {
        "paths": 0,
        "flatIntVars": 590,
        "flatIntConstraints": 835,
        "evaluatedHalfReifiedConstraints": 294,
        "method": "satisfy",
        "flatTime": 105.12100000000001,
        "nodes": 1,
        "solveTime": 140.0,
        "time": 136.0,
        "nSolutions": 1,
        "lower_gap_ini": {
            "lower": 12493,
            "upper": 14205
        },
        "gap_end": {
            "lower": 12493,
            "upper": 14205
        }
    }
}