{
    "status": "ALL_SOLUTIONS",
    "solution": {
        "start_time": [
            [
                12132,
                108,
                275,
                319,
                12152,
                8,
                529,
                186,
                550
            ],
            [
                12067,
                12061,
                12078,
                135,
                84,
                12124,
                168,
                0,
                234
            ],
            [
                0,
                89,
                134,
                108,
                201,
                171,
                7,
                42,
                63
            ],
            [
                500,
                182,
                258,
                39,
                134,
                0,
                514,
                68,
                127
            ],
            [
                45,
                39,
                12148,
                0,
                167,
                261,
                122,
                220,
                89
            ],
            [
                168,
                150,
                234,
                12139,
                0,
                245,
                49,
                105,
                221
            ],
            [
                15,
                0,
                245,
                261,
                49,
                186,
                30,
                150,
                206
            ]
        ],
        "end_time": [
            [
                12152,
                118,
                318,
                325,
                12170,
                39,
                550,
                220,
                589
            ],
            [
                12078,
                12067,
                12124,
                166,
                116,
                12170,
                198,
                42,
                254
            ],
            [
                7,
                108,
                171,
                134,
                223,
                182,
                30,
                63,
                89
            ],
            [
                514,
                225,
                275,
                68,
                160,
                8,
                529,
                105,
                134
            ],
            [
                61,
                45,
                12170,
                39,
                190,
                279,
                167,
                251,
                122
            ],
            [
                207,
                168,
                245,
                12170,
                24,
                260,
                91,
                150,
                234
            ],
            [
                22,
                15,
                258,
                291,
                69,
                206,
                49,
                186,
                221
            ]
        ],
        "SpeedScaling": [
            [
                3,
                3,
                3,
                3,
                3,
                3,
                3,
                3,
                3
            ],
            [
                3,
                3,
                3,
                3,
                3,
                3,
                3,
                3,
                3
            ],
            [
                3,
                3,
                3,
                3,
                3,
                3,
                3,
                3,
                3
            ],
            [
                3,
                3,
                3,
                3,
                3,
                3,
                3,
                3,
                3
            ],
            [
                3,
                3,
                3,
                3,
                3,
                3,
                3,
                3,
                3
            ],
            [
                3,
                3,
                3,
                3,
                3,
                3,
                3,
                3,
                3
            ],
            [
                3,
                3,
                3,
                3,
                3,
                3,
                3,
                3,
                3
            ]
        ],
        "_output_item": "makespan=12170\nenergy=4957\nidle=108010\nstart_times = [12132, 108, 275, 319, 12152, 8, 529, 186, 550, 12067, 12061, 12078, 135, 84, 12124, 168, 0, 234, 0, 89, 134, 108, 201, 171, 7, 42, 63, 500, 182, 258, 39, 134, 0, 514, 68, 127, 45, 39, 12148, 0, 167, 261, 122, 220, 89, 168, 150, 234, 12139, 0, 245, 49, 105, 221, 15, 0, 245, 261, 49, 186, 30, 150, 206]\nend_times =[12152, 118, 318, 325, 12170, 39, 550, 220, 589, 12078, 12067, 12124, 166, 116, 12170, 198, 42, 254, 7, 108, 171, 134, 223, 182, 30, 63, 89, 514, 225, 275, 68, 160, 8, 529, 105, 134, 61, 45, 12170, 39, 190, 279, 167, 251, 122, 207, 168, 245, 12170, 24, 260, 91, 150, 234, 22, 15, 258, 291, 69, 206, 49, 186, 221]\nspeed_assignment =[3, 3, 3, 3, 3, 3, 3, 3, 3, 3, 3, 3, 3, 3, 3, 3, 3, 3, 3, 3, 3, 3, 3, 3, 3, 3, 3, 3, 3, 3, 3, 3, 3, 3, 3, 3, 3, 3, 3, 3, 3, 3, 3, 3, 3, 3, 3, 3, 3, 3, 3, 3, 3, 3, 3, 3, 3, 3, 3, 3, 3, 3, 3]\ntimepro =[113, 27, 20, 58, 14, 10, 241, 59, 43, 36, 8, 6, 103, 25, 18, 172, 42, 31, 122, 29, 21, 193, 47, 34, 219, 53, 39, 61, 15, 11, 36, 8, 6, 255, 62, 46, 174, 42, 31, 178, 43, 32, 258, 63, 46, 168, 41, 30, 233, 57, 42, 115, 28, 20, 41, 10, 7, 109, 26, 19, 206, 50, 37, 149, 36, 26, 124, 30, 22, 61, 14, 11, 129, 31, 23, 118, 29, 21, 148, 36, 26, 78, 19, 14, 241, 59, 43, 97, 23, 17, 164, 40, 29, 149, 36, 26, 49, 12, 8, 83, 20, 15, 210, 51, 37, 39, 9, 7, 89, 21, 16, 34, 8, 6, 125, 30, 22, 217, 53, 39, 130, 31, 23, 102, 24, 18, 251, 61, 45, 176, 43, 31, 183, 45, 33, 221, 54, 39, 104, 25, 18, 65, 15, 11, 176, 43, 31, 136, 33, 24, 84, 20, 15, 236, 57, 42, 250, 61, 45, 76, 18, 13, 39, 9, 7, 85, 20, 15, 74, 18, 13, 167, 41, 30, 114, 28, 20, 115, 28, 20, 108, 26, 19, 201, 49, 36, 86, 21, 15]\n",
        "_checker": ""
    },
    "statistics": {
        "paths": 0,
        "flatBoolVars": 378,
        "flatIntVars": 324,
        "flatBoolConstraints": 189,
        "flatIntConstraints": 835,
        "evaluatedHalfReifiedConstraints": 378,
        "method": "satisfy",
        "flatTime": 81.993,
        "time": 169.0,
        "nSolutions": 1,
        "objective": 0,
        "objectiveBound": 0,
        "boolVariables": 210,
        "failures": 0,
        "propagations": 4274,
        "solveTime": 45.589999999999996,
        "lower_gap_ini": {
            "lower": 19615,
            "upper": 22571
        },
        "gap_end": {
            "lower": 19615,
            "upper": 22571
        }
    }
}