{
    "status": "SATISFIED",
    "solution": {
        "start_time": [
            [
                3231,
                3123,
                0,
                67,
                265,
                3164,
                3310,
                345
            ],
            [
                206,
                242,
                67,
                3544,
                0,
                3421,
                3448,
                3275
            ],
            [
                21,
                3431,
                3441,
                136,
                3310,
                3504,
                3100,
                3192
            ],
            [
                3193,
                129,
                3505,
                3443,
                345,
                483,
                426,
                3537
            ],
            [
                0,
                330,
                166,
                176,
                85,
                21,
                483,
                274
            ],
            [
                134,
                0,
                265,
                3331,
                206,
                86,
                3297,
                3494
            ],
            [
                3564,
                3344,
                3187,
                274,
                3395,
                210,
                10,
                0
            ],
            [
                3342,
                86,
                3274,
                3389,
                3493,
                164,
                3404,
                129
            ]
        ],
        "end_time": [
            [
                3310,
                3164,
                67,
                136,
                345,
                3231,
                3404,
                405
            ],
            [
                242,
                313,
                159,
                3576,
                43,
                3448,
                3544,
                3353
            ],
            [
                80,
                3441,
                3504,
                148,
                3395,
                3576,
                3192,
                3275
            ],
            [
                3217,
                210,
                3537,
                3505,
                426,
                501,
                483,
                3576
            ],
            [
                21,
                408,
                176,
                274,
                166,
                85,
                548,
                330
            ],
            [
                206,
                86,
                313,
                3389,
                265,
                134,
                3310,
                3537
            ],
            [
                3576,
                3395,
                3274,
                330,
                3493,
                260,
                39,
                10
            ],
            [
                3389,
                129,
                3342,
                3404,
                3576,
                210,
                3448,
                164
            ]
        ],
        "SpeedScaling": [
            [
                1,
                1,
                1,
                1,
                1,
                1,
                1,
                1
            ],
            [
                1,
                1,
                1,
                1,
                1,
                1,
                1,
                1
            ],
            [
                1,
                1,
                1,
                1,
                1,
                1,
                1,
                1
            ],
            [
                1,
                1,
                1,
                1,
                1,
                1,
                1,
                1
            ],
            [
                1,
                1,
                1,
                1,
                1,
                1,
                1,
                1
            ],
            [
                1,
                1,
                1,
                1,
                1,
                1,
                1,
                1
            ],
            [
                1,
                1,
                1,
                1,
                1,
                1,
                1,
                1
            ],
            [
                1,
                1,
                1,
                1,
                1,
                1,
                1,
                1
            ]
        ],
        "_output_item": "makespan=3576\nenergy=3750\nidle=25032\nstart_times = [3231, 3123, 0, 67, 265, 3164, 3310, 345, 206, 242, 67, 3544, 0, 3421, 3448, 3275, 21, 3431, 3441, 136, 3310, 3504, 3100, 3192, 3193, 129, 3505, 3443, 345, 483, 426, 3537, 0, 330, 166, 176, 85, 21, 483, 274, 134, 0, 265, 3331, 206, 86, 3297, 3494, 3564, 3344, 3187, 274, 3395, 210, 10, 0, 3342, 86, 3274, 3389, 3493, 164, 3404, 129]\nend_times =[3310, 3164, 67, 136, 345, 3231, 3404, 405, 242, 313, 159, 3576, 43, 3448, 3544, 3353, 80, 3441, 3504, 148, 3395, 3576, 3192, 3275, 3217, 210, 3537, 3505, 426, 501, 483, 3576, 21, 408, 176, 274, 166, 85, 548, 330, 206, 86, 313, 3389, 265, 134, 3310, 3537, 3576, 3395, 3274, 330, 3493, 260, 39, 10, 3389, 129, 3342, 3404, 3576, 210, 3448, 164]\nspeed_assignment =[1, 1, 1, 1, 1, 1, 1, 1, 1, 1, 1, 1, 1, 1, 1, 1, 1, 1, 1, 1, 1, 1, 1, 1, 1, 1, 1, 1, 1, 1, 1, 1, 1, 1, 1, 1, 1, 1, 1, 1, 1, 1, 1, 1, 1, 1, 1, 1, 1, 1, 1, 1, 1, 1, 1, 1, 1, 1, 1, 1, 1, 1, 1, 1]\ntimepro =[79, 41, 67, 69, 80, 67, 94, 60, 36, 71, 92, 32, 43, 27, 96, 78, 59, 10, 63, 12, 85, 72, 92, 83, 24, 81, 32, 62, 81, 18, 57, 39, 21, 78, 10, 98, 81, 64, 65, 56, 72, 86, 48, 58, 59, 48, 13, 43, 12, 51, 87, 56, 98, 50, 29, 10, 47, 43, 68, 15, 83, 46, 44, 35]\n",
        "_checker": ""
    },
    "statistics": {
        "paths": 0,
        "flatIntVars": 642,
        "flatIntConstraints": 1090,
        "evaluatedHalfReifiedConstraints": 448,
        "method": "satisfy",
        "flatTime": 121.024,
        "nodes": 0,
        "solveTime": 8.0,
        "time": 149.0,
        "openNodes": 1,
        "nSolutions": 1,
        "lower_gap_ini": {
            "lower": 27172,
            "upper": 29550
        },
        "gap_end": {
            "lower": 27172,
            "upper": 29550
        }
    }
}