{
    "status": "ALL_SOLUTIONS",
    "solution": {
        "start_time": [
            [
                3403,
                3295,
                499,
                3086,
                3155,
                3336,
                3482,
                3235
            ],
            [
                330,
                366,
                219,
                3544,
                0,
                515,
                543,
                437
            ],
            [
                21,
                542,
                598,
                80,
                390,
                661,
                92,
                184
            ],
            [
                374,
                43,
                566,
                462,
                167,
                343,
                286,
                3537
            ],
            [
                0,
                571,
                329,
                364,
                248,
                124,
                650,
                515
            ],
            [
                258,
                124,
                451,
                524,
                330,
                210,
                502,
                582
            ],
            [
                600,
                451,
                364,
                308,
                502,
                258,
                10,
                0
            ],
            [
                202,
                0,
                134,
                249,
                3493,
                78,
                433,
                43
            ]
        ],
        "end_time": [
            [
                3482,
                3336,
                566,
                3155,
                3235,
                3403,
                3576,
                3295
            ],
            [
                366,
                437,
                311,
                3576,
                43,
                542,
                639,
                515
            ],
            [
                80,
                552,
                661,
                92,
                475,
                733,
                184,
                267
            ],
            [
                398,
                124,
                598,
                524,
                248,
                361,
                343,
                3576
            ],
            [
                21,
                649,
                339,
                462,
                329,
                188,
                715,
                571
            ],
            [
                330,
                210,
                499,
                582,
                389,
                258,
                515,
                625
            ],
            [
                612,
                502,
                451,
                364,
                600,
                308,
                39,
                10
            ],
            [
                249,
                43,
                202,
                264,
                3576,
                124,
                477,
                78
            ]
        ],
        "SpeedScaling": [
            [
                1,
                1,
                1,
                1,
                1,
                1,
                1,
                1
            ],
            [
                1,
                1,
                1,
                1,
                1,
                1,
                1,
                1
            ],
            [
                1,
                1,
                1,
                1,
                1,
                1,
                1,
                1
            ],
            [
                1,
                1,
                1,
                1,
                1,
                1,
                1,
                1
            ],
            [
                1,
                1,
                1,
                1,
                1,
                1,
                1,
                1
            ],
            [
                1,
                1,
                1,
                1,
                1,
                1,
                1,
                1
            ],
            [
                1,
                1,
                1,
                1,
                1,
                1,
                1,
                1
            ],
            [
                1,
                1,
                1,
                1,
                1,
                1,
                1,
                1
            ]
        ],
        "_output_item": "makespan=3576\nenergy=3750\nidle=25032\nstart_times = [3403, 3295, 499, 3086, 3155, 3336, 3482, 3235, 330, 366, 219, 3544, 0, 515, 543, 437, 21, 542, 598, 80, 390, 661, 92, 184, 374, 43, 566, 462, 167, 343, 286, 3537, 0, 571, 329, 364, 248, 124, 650, 515, 258, 124, 451, 524, 330, 210, 502, 582, 600, 451, 364, 308, 502, 258, 10, 0, 202, 0, 134, 249, 3493, 78, 433, 43]\nend_times =[3482, 3336, 566, 3155, 3235, 3403, 3576, 3295, 366, 437, 311, 3576, 43, 542, 639, 515, 80, 552, 661, 92, 475, 733, 184, 267, 398, 124, 598, 524, 248, 361, 343, 3576, 21, 649, 339, 462, 329, 188, 715, 571, 330, 210, 499, 582, 389, 258, 515, 625, 612, 502, 451, 364, 600, 308, 39, 10, 249, 43, 202, 264, 3576, 124, 477, 78]\nspeed_assignment =[1, 1, 1, 1, 1, 1, 1, 1, 1, 1, 1, 1, 1, 1, 1, 1, 1, 1, 1, 1, 1, 1, 1, 1, 1, 1, 1, 1, 1, 1, 1, 1, 1, 1, 1, 1, 1, 1, 1, 1, 1, 1, 1, 1, 1, 1, 1, 1, 1, 1, 1, 1, 1, 1, 1, 1, 1, 1, 1, 1, 1, 1, 1, 1]\ntimepro =[79, 41, 67, 69, 80, 67, 94, 60, 36, 71, 92, 32, 43, 27, 96, 78, 59, 10, 63, 12, 85, 72, 92, 83, 24, 81, 32, 62, 81, 18, 57, 39, 21, 78, 10, 98, 81, 64, 65, 56, 72, 86, 48, 58, 59, 48, 13, 43, 12, 51, 87, 56, 98, 50, 29, 10, 47, 43, 68, 15, 83, 46, 44, 35]\n",
        "_checker": ""
    },
    "statistics": {
        "paths": 0,
        "flatBoolVars": 448,
        "flatIntVars": 130,
        "flatBoolConstraints": 224,
        "flatIntConstraints": 749,
        "evaluatedHalfReifiedConstraints": 448,
        "method": "satisfy",
        "flatTime": 81.0,
        "time": 161.0,
        "nSolutions": 1,
        "objective": 0,
        "objectiveBound": 0,
        "boolVariables": 224,
        "failures": 0,
        "propagations": 7731,
        "solveTime": 37.827,
        "lower_gap_ini": {
            "lower": 27172,
            "upper": 29550
        },
        "gap_end": {
            "lower": 27172,
            "upper": 29550
        }
    }
}