{
    "status": "SATISFIED",
    "solution": {
        "start_time": [
            [
                20,
                29,
                0,
                56
            ],
            [
                87,
                124,
                164,
                237
            ],
            [
                41,
                87,
                20,
                0
            ],
            [
                235,
                225,
                185,
                15
            ],
            [
                285,
                235,
                276,
                329
            ],
            [
                108,
                350,
                285,
                343
            ],
            [
                329,
                276,
                492,
                478
            ],
            [
                114,
                376,
                418,
                458
            ],
            [
                134,
                418,
                225,
                350
            ]
        ],
        "end_time": [
            [
                29,
                56,
                20,
                237
            ],
            [
                108,
                164,
                185,
                243
            ],
            [
                87,
                124,
                41,
                15
            ],
            [
                247,
                235,
                225,
                41
            ],
            [
                329,
                276,
                285,
                343
            ],
            [
                114,
                376,
                327,
                350
            ],
            [
                371,
                315,
                534,
                492
            ],
            [
                134,
                418,
                458,
                478
            ],
            [
                145,
                471,
                239,
                366
            ]
        ],
        "SpeedScaling": [
            [
                5,
                5,
                5,
                1
            ],
            [
                5,
                5,
                5,
                5
            ],
            [
                5,
                5,
                5,
                5
            ],
            [
                5,
                5,
                5,
                5
            ],
            [
                5,
                5,
                5,
                5
            ],
            [
                5,
                5,
                5,
                5
            ],
            [
                5,
                5,
                5,
                5
            ],
            [
                5,
                5,
                5,
                5
            ],
            [
                5,
                1,
                5,
                5
            ]
        ],
        "_output_item": "makespan=534\nenergy=2739\nidle=1062\nstart_times = [20, 29, 0, 56, 87, 124, 164, 237, 41, 87, 20, 0, 235, 225, 185, 15, 285, 235, 276, 329, 108, 350, 285, 343, 329, 276, 492, 478, 114, 376, 418, 458, 134, 418, 225, 350]\nend_times =[29, 56, 20, 237, 108, 164, 185, 243, 87, 124, 41, 15, 247, 235, 225, 41, 329, 276, 285, 343, 114, 376, 327, 350, 371, 315, 534, 492, 134, 418, 458, 478, 145, 471, 239, 366]\nspeed_assignment =[5, 5, 5, 1, 5, 5, 5, 5, 5, 5, 5, 5, 5, 5, 5, 5, 5, 5, 5, 5, 5, 5, 5, 5, 5, 5, 5, 5, 5, 5, 5, 5, 5, 1, 5, 5]\ntimepro =[52, 17, 12, 10, 9, 153, 53, 37, 31, 27, 113, 39, 27, 23, 20, 181, 62, 44, 37, 32, 118, 41, 29, 24, 21, 225, 77, 55, 45, 40, 121, 41, 29, 24, 21, 33, 11, 8, 6, 6, 257, 88, 62, 52, 46, 205, 71, 50, 41, 37, 119, 41, 29, 24, 21, 86, 29, 21, 17, 15, 71, 24, 17, 14, 12, 58, 20, 14, 11, 10, 226, 78, 55, 46, 40, 144, 49, 35, 29, 26, 249, 86, 61, 50, 44, 228, 78, 55, 46, 41, 52, 18, 12, 10, 9, 82, 28, 20, 16, 14, 34, 12, 8, 7, 6, 149, 51, 36, 30, 26, 236, 81, 57, 48, 42, 40, 13, 9, 8, 7, 237, 82, 58, 48, 42, 217, 74, 53, 44, 39, 235, 81, 57, 47, 42, 78, 27, 19, 15, 14, 115, 39, 28, 23, 20, 236, 81, 57, 48, 42, 224, 77, 54, 45, 40, 114, 39, 27, 23, 20, 66, 22, 16, 13, 11, 53, 18, 13, 10, 9, 80, 27, 19, 16, 14, 91, 31, 22, 18, 16]\n",
        "_checker": ""
    },
    "statistics": {
        "paths": 0,
        "flatIntVars": 686,
        "flatIntConstraints": 740,
        "evaluatedHalfReifiedConstraints": 288,
        "method": "satisfy",
        "flatTime": 111.28,
        "nodes": 0,
        "solveTime": 94.0,
        "time": 226.0,
        "nSolutions": 1,
        "lower_gap_ini": {
            "lower": 4399,
            "upper": 5285
        },
        "gap_end": {
            "lower": 4399,
            "upper": 5285
        }
    }
}