{
    "status": "ALL_SOLUTIONS",
    "solution": {
        "start_time": [
            [
                20981,
                198,
                21027,
                273,
                243,
                95,
                46,
                20998
            ],
            [
                18,
                20975,
                293,
                237,
                21016,
                171,
                118,
                111
            ],
            [
                165,
                283,
                84,
                78,
                125,
                206,
                21027,
                37
            ],
            [
                21004,
                135,
                339,
                36,
                0,
                21025,
                276,
                212
            ],
            [
                51,
                36,
                277,
                0,
                199,
                266,
                259,
                294
            ],
            [
                187,
                0,
                39,
                231,
                165,
                50,
                266,
                24
            ],
            [
                97,
                264,
                227,
                212,
                183,
                0,
                18,
                199
            ],
            [
                0,
                51,
                353,
                293,
                85,
                18,
                227,
                259
            ],
            [
                173,
                100,
                0,
                167,
                265,
                135,
                187,
                78
            ]
        ],
        "end_time": [
            [
                20998,
                243,
                21052,
                281,
                265,
                107,
                85,
                21027
            ],
            [
                39,
                21016,
                339,
                272,
                21052,
                206,
                143,
                118
            ],
            [
                171,
                312,
                125,
                82,
                165,
                234,
                21052,
                78
            ],
            [
                21025,
                174,
                352,
                78,
                30,
                21052,
                305,
                252
            ],
            [
                90,
                51,
                293,
                36,
                243,
                277,
                266,
                313
            ],
            [
                231,
                24,
                50,
                237,
                183,
                95,
                275,
                37
            ],
            [
                138,
                283,
                264,
                227,
                199,
                18,
                46,
                212
            ],
            [
                18,
                85,
                397,
                297,
                125,
                50,
                259,
                292
            ],
            [
                187,
                135,
                34,
                173,
                303,
                167,
                227,
                100
            ]
        ],
        "SpeedScaling": [
            [
                5,
                5,
                5,
                5,
                5,
                5,
                5,
                5
            ],
            [
                5,
                5,
                5,
                5,
                5,
                5,
                5,
                5
            ],
            [
                5,
                5,
                5,
                5,
                5,
                5,
                5,
                5
            ],
            [
                5,
                5,
                5,
                5,
                5,
                5,
                5,
                5
            ],
            [
                5,
                5,
                5,
                5,
                5,
                5,
                4,
                5
            ],
            [
                5,
                5,
                5,
                5,
                5,
                5,
                5,
                5
            ],
            [
                5,
                5,
                5,
                5,
                5,
                5,
                5,
                5
            ],
            [
                5,
                5,
                5,
                5,
                5,
                5,
                5,
                5
            ],
            [
                5,
                5,
                5,
                5,
                5,
                5,
                5,
                5
            ]
        ],
        "_output_item": "makespan=21052\nenergy=5541\nidle=166516\nstart_times = [20981, 198, 21027, 273, 243, 95, 46, 20998, 18, 20975, 293, 237, 21016, 171, 118, 111, 165, 283, 84, 78, 125, 206, 21027, 37, 21004, 135, 339, 36, 0, 21025, 276, 212, 51, 36, 277, 0, 199, 266, 259, 294, 187, 0, 39, 231, 165, 50, 266, 24, 97, 264, 227, 212, 183, 0, 18, 199, 0, 51, 353, 293, 85, 18, 227, 259, 173, 100, 0, 167, 265, 135, 187, 78]\nend_times =[20998, 243, 21052, 281, 265, 107, 85, 21027, 39, 21016, 339, 272, 21052, 206, 143, 118, 171, 312, 125, 82, 165, 234, 21052, 78, 21025, 174, 352, 78, 30, 21052, 305, 252, 90, 51, 293, 36, 243, 277, 266, 313, 231, 24, 50, 237, 183, 95, 275, 37, 138, 283, 264, 227, 199, 18, 46, 212, 18, 85, 397, 297, 125, 50, 259, 292, 187, 135, 34, 173, 303, 167, 227, 100]\nspeed_assignment =[5, 5, 5, 5, 5, 5, 5, 5, 5, 5, 5, 5, 5, 5, 5, 5, 5, 5, 5, 5, 5, 5, 5, 5, 5, 5, 5, 5, 5, 5, 5, 5, 5, 5, 5, 5, 5, 5, 4, 5, 5, 5, 5, 5, 5, 5, 5, 5, 5, 5, 5, 5, 5, 5, 5, 5, 5, 5, 5, 5, 5, 5, 5, 5, 5, 5, 5, 5, 5, 5, 5, 5]\ntimepro =[95, 33, 23, 19, 17, 252, 87, 61, 51, 45, 140, 48, 34, 28, 25, 49, 16, 12, 9, 8, 122, 42, 29, 24, 22, 71, 24, 17, 14, 12, 221, 76, 54, 45, 39, 164, 56, 40, 33, 29, 119, 41, 29, 24, 21, 230, 79, 56, 46, 41, 256, 88, 62, 52, 46, 198, 68, 48, 40, 35, 202, 70, 49, 41, 36, 198, 68, 48, 40, 35, 140, 48, 34, 28, 25, 40, 14, 10, 8, 7, 38, 13, 9, 7, 6, 165, 57, 40, 33, 29, 229, 79, 56, 46, 41, 26, 8, 6, 5, 4, 223, 77, 54, 45, 40, 156, 54, 38, 31, 28, 143, 49, 35, 29, 25, 233, 80, 57, 47, 41, 121, 42, 29, 24, 21, 217, 75, 53, 44, 39, 75, 26, 18, 15, 13, 238, 82, 58, 48, 42, 170, 59, 41, 34, 30, 150, 51, 36, 30, 27, 164, 56, 40, 33, 29, 223, 77, 54, 45, 40, 217, 75, 53, 44, 39, 84, 29, 20, 17, 15, 89, 30, 21, 18, 16, 203, 70, 49, 41, 36, 244, 84, 60, 49, 44, 62, 21, 15, 12, 11, 39, 13, 9, 7, 7, 107, 37, 26, 21, 19, 248, 85, 60, 50, 44, 136, 47, 33, 27, 24, 63, 21, 15, 12, 11, 35, 12, 8, 7, 6, 104, 36, 25, 21, 18, 255, 88, 62, 51, 45, 51, 17, 12, 10, 9, 73, 25, 17, 14, 13, 231, 80, 56, 47, 41, 109, 37, 26, 22, 19, 210, 72, 51, 42, 37, 85, 29, 20, 17, 15, 91, 31, 22, 18, 16, 100, 34, 24, 20, 18, 157, 54, 38, 31, 28, 74, 25, 18, 15, 13, 102, 35, 25, 20, 18, 193, 66, 47, 39, 34, 249, 86, 61, 50, 44, 26, 9, 6, 5, 4, 226, 78, 55, 46, 40, 181, 62, 44, 36, 32, 181, 62, 44, 36, 32, 184, 63, 45, 37, 33, 81, 27, 19, 16, 14, 198, 68, 48, 40, 35, 190, 65, 46, 38, 34, 37, 13, 9, 7, 6, 213, 73, 52, 43, 38, 179, 61, 43, 36, 32, 225, 77, 55, 45, 40, 122, 42, 30, 24, 22]\n",
        "_checker": ""
    },
    "statistics": {
        "paths": 0,
        "flatBoolVars": 576,
        "flatIntVars": 362,
        "flatBoolConstraints": 288,
        "flatIntConstraints": 1046,
        "evaluatedHalfReifiedConstraints": 576,
        "method": "satisfy",
        "flatTime": 84.783,
        "time": 178.0,
        "nSolutions": 1,
        "objective": 0,
        "objectiveBound": 0,
        "boolVariables": 288,
        "failures": 0,
        "propagations": 5638,
        "solveTime": 45.847,
        "lower_gap_ini": {
            "lower": -3143,
            "upper": 14647
        },
        "gap_end": {
            "lower": -3143,
            "upper": 14647
        }
    }
}