{
    "status": "SATISFIED",
    "solution": {
        "start_time": [
            [
                0,
                160,
                138,
                123,
                80,
                104,
                51,
                197,
                14
            ],
            [
                25,
                0,
                98,
                138,
                144,
                158,
                110,
                53,
                120
            ],
            [
                421,
                25,
                160,
                195,
                485,
                441,
                383,
                343,
                450
            ],
            [
                469,
                503,
                195,
                429,
                0,
                417,
                373,
                383,
                51
            ],
            [
                441,
                244,
                236,
                0,
                288,
                36,
                454,
                326,
                294
            ],
            [
                503,
                288,
                457,
                65,
                29,
                57,
                0,
                417,
                86
            ],
            [
                454,
                332,
                372,
                56,
                528,
                568,
                421,
                460,
                498
            ],
            [
                136,
                96,
                581,
                558,
                158,
                450,
                80,
                599,
                528
            ],
            [
                53,
                635,
                599,
                623,
                568,
                0,
                29,
                498,
                126
            ]
        ],
        "end_time": [
            [
                14,
                197,
                160,
                138,
                104,
                123,
                80,
                232,
                51
            ],
            [
                53,
                25,
                110,
                144,
                158,
                362,
                120,
                98,
                126
            ],
            [
                441,
                65,
                195,
                212,
                496,
                450,
                421,
                383,
                485
            ],
            [
                503,
                526,
                236,
                469,
                27,
                429,
                383,
                417,
                84
            ],
            [
                454,
                288,
                244,
                36,
                294,
                57,
                493,
                343,
                326
            ],
            [
                541,
                332,
                478,
                86,
                49,
                65,
                29,
                457,
                101
            ],
            [
                460,
                372,
                386,
                65,
                568,
                693,
                429,
                498,
                528
            ],
            [
                148,
                136,
                599,
                581,
                177,
                489,
                96,
                636,
                558
            ],
            [
                90,
                662,
                623,
                635,
                592,
                23,
                39,
                543,
                150
            ]
        ],
        "SpeedScaling": [
            [
                4,
                4,
                4,
                4,
                4,
                4,
                4,
                4,
                4
            ],
            [
                4,
                4,
                4,
                4,
                4,
                1,
                4,
                4,
                4
            ],
            [
                4,
                4,
                4,
                4,
                3,
                4,
                4,
                4,
                4
            ],
            [
                4,
                4,
                4,
                4,
                4,
                4,
                4,
                4,
                4
            ],
            [
                4,
                4,
                4,
                4,
                4,
                4,
                1,
                4,
                4
            ],
            [
                3,
                4,
                4,
                4,
                4,
                4,
                4,
                4,
                4
            ],
            [
                4,
                4,
                4,
                4,
                4,
                1,
                4,
                4,
                4
            ],
            [
                4,
                4,
                4,
                4,
                4,
                4,
                4,
                4,
                4
            ],
            [
                4,
                4,
                4,
                4,
                4,
                4,
                4,
                4,
                4
            ]
        ],
        "_output_item": "makespan=693\nenergy=6204\nidle=3934\nstart_times = [0, 160, 138, 123, 80, 104, 51, 197, 14, 25, 0, 98, 138, 144, 158, 110, 53, 120, 421, 25, 160, 195, 485, 441, 383, 343, 450, 469, 503, 195, 429, 0, 417, 373, 383, 51, 441, 244, 236, 0, 288, 36, 454, 326, 294, 503, 288, 457, 65, 29, 57, 0, 417, 86, 454, 332, 372, 56, 528, 568, 421, 460, 498, 136, 96, 581, 558, 158, 450, 80, 599, 528, 53, 635, 599, 623, 568, 0, 29, 498, 126]\nend_times =[14, 197, 160, 138, 104, 123, 80, 232, 51, 53, 25, 110, 144, 158, 362, 120, 98, 126, 441, 65, 195, 212, 496, 450, 421, 383, 485, 503, 526, 236, 469, 27, 429, 383, 417, 84, 454, 288, 244, 36, 294, 57, 493, 343, 326, 541, 332, 478, 86, 49, 65, 29, 457, 101, 460, 372, 386, 65, 568, 693, 429, 498, 528, 148, 136, 599, 581, 177, 489, 96, 636, 558, 90, 662, 623, 635, 592, 23, 39, 543, 150]\nspeed_assignment =[4, 4, 4, 4, 4, 4, 4, 4, 4, 4, 4, 4, 4, 4, 1, 4, 4, 4, 4, 4, 4, 4, 3, 4, 4, 4, 4, 4, 4, 4, 4, 4, 4, 4, 4, 4, 4, 4, 4, 4, 4, 4, 1, 4, 4, 3, 4, 4, 4, 4, 4, 4, 4, 4, 4, 4, 4, 4, 4, 1, 4, 4, 4, 4, 4, 4, 4, 4, 4, 4, 4, 4, 4, 4, 4, 4, 4, 4, 4, 4, 4]\ntimepro =[79, 23, 16, 14, 205, 61, 44, 37, 126, 37, 27, 22, 88, 26, 18, 15, 138, 41, 29, 24, 110, 33, 23, 19, 166, 49, 35, 29, 195, 58, 41, 35, 207, 61, 44, 37, 157, 46, 33, 28, 140, 42, 30, 25, 68, 20, 14, 12, 36, 10, 7, 6, 81, 24, 17, 14, 204, 61, 43, 36, 58, 17, 12, 10, 253, 75, 54, 45, 34, 10, 7, 6, 115, 34, 24, 20, 224, 67, 48, 40, 197, 58, 42, 35, 96, 28, 20, 17, 53, 15, 11, 9, 54, 16, 11, 9, 214, 64, 45, 38, 227, 67, 48, 40, 199, 59, 42, 35, 189, 56, 40, 34, 128, 38, 27, 23, 228, 68, 48, 41, 222, 66, 47, 40, 152, 45, 32, 27, 70, 21, 15, 12, 58, 17, 12, 10, 191, 57, 40, 34, 185, 55, 39, 33, 76, 22, 16, 13, 245, 73, 52, 44, 49, 14, 10, 8, 202, 60, 43, 36, 34, 10, 7, 6, 118, 35, 25, 21, 39, 11, 8, 7, 99, 29, 21, 17, 181, 54, 38, 32, 179, 53, 38, 32, 248, 74, 53, 44, 117, 35, 25, 21, 122, 36, 26, 21, 111, 33, 23, 20, 49, 14, 10, 8, 165, 49, 35, 29, 224, 67, 48, 40, 87, 26, 18, 15, 38, 11, 8, 6, 227, 67, 48, 40, 82, 24, 17, 14, 50, 14, 10, 9, 223, 66, 48, 40, 125, 37, 26, 22, 44, 13, 9, 8, 213, 63, 45, 38, 169, 50, 36, 30, 72, 21, 15, 12, 222, 66, 47, 40, 104, 31, 22, 18, 129, 38, 27, 23, 109, 32, 23, 19, 217, 65, 46, 39, 91, 27, 19, 16, 208, 62, 44, 37, 170, 50, 36, 30, 207, 62, 44, 37, 154, 46, 33, 27, 136, 40, 29, 24, 69, 20, 14, 12, 137, 41, 29, 24, 132, 39, 28, 23, 59, 17, 12, 10, 252, 75, 54, 45, 137, 41, 29, 24]\n",
        "_checker": ""
    },
    "statistics": {
        "paths": 0,
        "flatIntVars": 1460,
        "flatIntConstraints": 1865,
        "evaluatedHalfReifiedConstraints": 648,
        "method": "satisfy",
        "flatTime": 196.046,
        "nodes": 0,
        "solveTime": 148.0,
        "time": 371.0,
        "nSolutions": 1,
        "lower_gap_ini": {
            "lower": -2653,
            "upper": 22763
        },
        "gap_end": {
            "lower": -2653,
            "upper": 22763
        }
    }
}